deskmaid/__init__.py
deskmaid/__main__.py
deskmaid/assets/kanna.ico
deskmaid/assets/thoru.ico
deskmaid/cli.py
deskmaid/config/config.yml
deskmaid/config.py
deskmaid/deskmaid.py
deskmaid/file.py
deskmaid/i18n.py
deskmaid/info.py
deskmaid/locale/en/LC_MESSAGES/messages.mo
deskmaid/locale/en/LC_MESSAGES/messages.po
deskmaid/locale/fr/LC_MESSAGES/messages.mo
deskmaid/locale/fr/LC_MESSAGES/messages.po
deskmaid/locale/messages.pot
deskmaid/py.typed
deskmaid-2.0.2.dist-info/LICENSE
deskmaid-2.0.2.dist-info/METADATA
deskmaid-2.0.2.dist-info/WHEEL
deskmaid-2.0.2.dist-info/entry_points.txt
deskmaid-2.0.2.dist-info/RECORD
