Metadata-Version: 2.1
Name: deskmaid
Version: 2.0.2
Summary: Configurable desktop cleaner.
Home-page: https://github.com/Dashstrom/deskmaid
License: MIT
Keywords: python,utility,script,desktop,cleaner
Author: Dashstrom
Author-email: dashstrom.pro@gmail.com
Maintainer: Dashstrom
Maintainer-email: dashstrom.pro@gmail.com
Requires-Python: >=3.8
Classifier: Development Status :: 4 - Beta
Classifier: Environment :: Console
Classifier: Framework :: Pytest
Classifier: Framework :: Sphinx
Classifier: Framework :: tox
Classifier: Intended Audience :: Developers
Classifier: Intended Audience :: System Administrators
Classifier: License :: OSI Approved :: MIT License
Classifier: Natural Language :: English
Classifier: Operating System :: OS Independent
Classifier: Programming Language :: Python :: 3
Classifier: Programming Language :: Python :: 3.8
Classifier: Programming Language :: Python :: 3.9
Classifier: Programming Language :: Python :: 3.10
Classifier: Programming Language :: Python :: 3.11
Classifier: Programming Language :: Python :: 3.12
Classifier: Programming Language :: Python :: 3 :: Only
Classifier: Typing :: Typed
Provides-Extra: cov
Provides-Extra: docs
Provides-Extra: format
Provides-Extra: lint
Provides-Extra: tasks
Provides-Extra: test
Requires-Dist: babel (==2.16.0) ; extra == "tasks"
Requires-Dist: commitizen (==3.28.0) ; extra == "tasks"
Requires-Dist: coverage[toml] (==7.6.0) ; extra == "cov"
Requires-Dist: msgspec
Requires-Dist: mypy (==1.11.1) ; extra == "lint" or extra == "format"
Requires-Dist: plyer
Requires-Dist: poethepoet (==0.27.0) ; extra == "tasks"
Requires-Dist: pre-commit (==3.5.0) ; extra == "tasks"
Requires-Dist: pre-commit-hooks (==4.6.0) ; extra == "tasks"
Requires-Dist: psutil
Requires-Dist: pytest (==8.3.2) ; extra == "test" or extra == "cov" or extra == "lint" or extra == "format"
Requires-Dist: pytest-cov (==5.0.0) ; extra == "cov"
Requires-Dist: pytest-mock (==3.14.0) ; extra == "test" or extra == "cov" or extra == "lint" or extra == "format"
Requires-Dist: pywin32 ; sys_platform == "win32"
Requires-Dist: pyyaml
Requires-Dist: ruff (==0.5.6) ; extra == "lint" or extra == "format"
Requires-Dist: sphinx (==7.1.2) ; extra == "docs"
Requires-Dist: sphinx-rtd-theme (==2.0.0) ; extra == "docs"
Requires-Dist: sphinxcontrib-mermaid (==0.9.2) ; extra == "docs"
Requires-Dist: types-pywin32 (==306.0.0.20240822) ; extra == "lint" or extra == "format"
Requires-Dist: typing-extensions (>=4.8.0)
Project-URL: Documentation, https://dashstrom.github.io/deskmaid
Project-URL: Repository, https://github.com/Dashstrom/deskmaid
